{
  "result": {
    "spreadsheetId": "1gVZnMr8DYtQROQMmyHUTlbJAyrOjRhzV0W1kAxfQ0wk",
    "valueRanges": [
      {
        "range": "'演出人員'!A1:Z997",
        "majorDimension": "ROWS",
        "values": [
          ["上台", "名稱", "樂器", "屆數"],
          ["", "中文姓名", "", "0,協演人員,-1,未知"],
          ["TRUE", "陳逸慧", "Flute", "28"],
          ["TRUE", "簡汎瑜", "Flute", "43"],
          ["TRUE", "林唯媛", "Flute", "45"],
          ["TRUE", "江品昀", "Flute", "47"],
          ["TRUE", "陳玟育", "Clarinet", "36"],
          ["TRUE", "翁育玟", "Clarinet", "37"],
          ["TRUE", "吳宜蓁", "Clarinet", "0"],
          ["TRUE", "呂晟智", "Clarinet", "0"],
          ["TRUE", "陳敬宗", "Clarinet", "0"],
          ["TRUE", "陳寶怡", "Clarinet", "0"],
          ["TRUE", "紀宇珊", "Alto Saxophone", "32"],
          ["TRUE", "張博翔", "Alto Saxophone", "43"],
          ["TRUE", "戴丰恬", "Alto Saxophone", "46"],
          ["TRUE", "謝嘉宜", "Alto Saxophone", "0"],
          ["TRUE", "劉宥成", "Tenor Saxophone", "0"],
          ["TRUE", "駱繹", "Baritone Saxophone", "35"],
          ["TRUE", "蘇育銘", "French horn", "27"],
          ["TRUE", "黃琬淑", "French horn", "31"],
          ["TRUE", "莊畇琦", "French horn", "48"],
          ["TRUE", "蘇雨桐", "French horn", "0"],
          ["TRUE", "白芷綾", "Trumpet", "0"],
          ["TRUE", "李浩維", "Trumpet", "0"],
          ["TRUE", "陳柏睿", "Trumpet", "0"],
          ["TRUE", "高煜", "Trombone", "34"],
          ["TRUE", "鄭兆廷", "Trombone", "33"],
          ["TRUE", "劉信成", "Trombone", "44"],
          ["TRUE", "林思亮", "Trombone", "48"],
          ["TRUE", "張明睿", "Euphonium", "26"],
          ["TRUE", "陳克齊", "Euphonium", "38"],
          ["TRUE", "陳函", "Euphonium", "0"],
          ["TRUE", "王妤萱", "Tuba", "40"],
          ["TRUE", "黃憫", "Tuba", "47"],
          ["TRUE", "李承霖", "Percussion", "37"],
          ["TRUE", "徐豊祺", "Percussion", "39"],
          ["TRUE", "陳可馨", "Percussion", "46"],
          ["TRUE", "鄭柏鳳", "Percussion", "46"],
          ["TRUE", "王晉維", "Percussion", "46"],
          ["TRUE", "吳承勳", "Percussion", "0"],
          ["TRUE", "陳逸安", "Piano", "0"]
        ]
      },
      {
        "range": "'流程'!A1:AA1001",
        "majorDimension": "ROWS",
        "values": [
          ["曲序", "公開活動", "曲目/活動", "小標題", "時間", "說明"],
          ["startFrom,1", "encore 就不用勾", "", "作曲人,補充說明", "分鐘 (曲目可略)"],
          [
            "1",
            "TRUE",
            "The Great Locomotive Chase",
            "Robert W. Smith",
            "",
            "描繪了一場發生在美國內戰期間的著名火車追逐事件，該事件是一次大膽的軍事行動，發生在1862年4月12日，由聯邦軍隊試圖奪取並摧毀南方邦聯的鐵路和補給線。\n一開始便展現出強烈的節奏感和緊張氣氛，模擬出火車的轟鳴聲和急速行駛的動態。隨著樂曲的發展，旋律變得越發激烈和充滿戲劇性，完美捕捉了追逐的緊迫感和緊張情勢。這首樂曲不僅展現了作曲家對歷史事件的深刻理解，也通過音樂的生動，再現了那段激動人心的歷史片段。"
          ],
          [
            "2",
            "TRUE",
            "春よ、来い",
            "鄉間幹男",
            "",
            "以溫柔而充滿情感的旋律著稱，表達了對春天到來的熱切期盼和對未來美好生活的憧憬。保留了原曲的細膩和溫暖，同時通過樂器間的配合與變化，賦予了它更多的層次感與表現力。當樂聲響起時，彷彿春天的氣息隨之撲面而來，為聽眾帶來無限的希望和美好的期待。"
          ],
          [
            "3",
            "TRUE",
            "The Lord of the Dance",
            "Richard Saucedo",
            "",
            "充滿活力與動感的作品，最初作為著名舞蹈劇《大河之舞》（Lord of the Dance）的主題曲而聞名。這首曲子以其強烈的節奏感和富有感染力的旋律，將愛爾蘭傳統音樂與現代編曲完美結合，是一首讓人不禁隨之起舞的動人作品。"
          ],
          [
            "4",
            "TRUE",
            "Curtain Up!",
            "Alfred Reed",
            "",
            "靈感來自於戲劇和音樂劇開場時的那份激動與期待感。正如其名，樂曲彷彿拉開了一場精彩表演的序幕，帶領聽眾進入一個充滿戲劇性和活力的音樂世界。\n序曲結構豐富，開頭以宏大且充滿戲劇性的旋律引導聽眾，隨後進入輕快、活潑的中段，展示出各種不同音樂風格的交織與變化。Reed運用了豐富的管樂編排技巧，讓每一個樂器組都能發揮其獨特的音色，從而營造出多層次的音樂效果。"
          ],
          [
            "5",
            "TRUE",
            "The Lion King",
            "John Higgins",
            "",
            "改編自迪士尼經典動畫《獅子王》的音樂，原作音樂由漢斯·季默（Hans Zimmer）和埃爾頓·約翰（Elton John）創作，旋律耳熟能詳，充滿非洲特色的節奏和旋律，將獅子王辛巴的冒險故事與生命循環的主題完美結合。這些曲目包括《Circle of Life》、《Hakuna Matata》、《Can You Feel the Love Tonight》等，皆已成為跨世代的經典。音樂在柔和與強烈之間不斷轉換，展現了從生命的開端到榮耀歸來的壯麗旅程。"
          ],
          ["", "TRUE", "中場休息", "休息 15 分鐘", "15"],
          [
            "6",
            "TRUE",
            "Symphonic Episode 1",
            "Satoshi Yagisawa",
            "",
            "樂曲的主題充滿戲劇性，從一開始便展現出莊嚴而充滿力量的氛圍。隨著音樂的推進，旋律逐漸變得緊湊和複雜，展現出作曲家精湛的編曲技巧。樂曲中穿插著細膩的抒情段落與強烈的音樂對比，從而構建了一個既有深度又富有動感的音樂旅程。"
          ],
          [
            "7",
            "TRUE",
            "Mulan",
            "Johnie Vinson",
            "",
            "電影《花木蘭》以中國古代的木蘭傳說為背景，描述了一位勇敢的少女木蘭女扮男裝替父從軍，最終成為英雄的故事，曲子完美融合了中國傳統音樂的元素與西方交響樂的氣勢。樂曲中既有柔美細膩的旋律，也有充滿張力的片段，生動地展現了木蘭從少女到戰士的成長歷程。"
          ],
          [
            "8",
            "TRUE",
            "J-POP Stage Vol-3",
            "山里佐和子",
            "",
            "著名日本動畫《海賊王》（One Piece）的經典樂曲組曲，匯集了動畫中多首耳熟能詳的曲目，通過管樂的形式重現了《海賊王》中那些充滿冒險、友情與夢想的感人時刻。音樂隨著劇情的發展而變化，時而激昂、時而抒情，完美捕捉了動畫中那股無畏的冒險精神和深厚的夥伴情誼。"
          ],
          [
            "9",
            "TRUE",
            " Idol",
            "",
            "",
            "日本動畫《我推的孩子》主題曲，以輕快的節奏、明亮的旋律和充滿青春氣息的編曲，生動地捕捉了流行音樂的精髓。旋律簡單卻極具吸引力，能夠讓人不由自主地跟隨節奏搖擺。"
          ],
          [
            "",
            "TRUE",
            "誠正校歌",
            "",
            "",
            "綠水長流　層山長青　斯地創校　毓秀鐘英\n復興文化　誠正是崇　我校其名　宏開世風\n健全國民　五育並重　仁為己任　善與人同\n莊敬自強　日新月盛　學以報國　治至以隆"
          ]
        ]
      },
      {
        "range": "'介紹'!A1:Y1001",
        "majorDimension": "ROWS",
        "values": [
          ["姓名", "職稱", "照片", "介紹", "quote"],
          ["", "", "請放連結", "長文介紹，用\",\"做分段"],
          [
            "林尚頤",
            "指揮",
            "https://i.imgur.com/YS3IFiS.jpeg",
            "臺北人，求學生涯曾就讀光仁小學、弘道國中、建國中學、臺北大學，並於大學時期初次接受正規指揮課程，師從王戰老師。除此之外，參加北大管樂團期間亦深受指揮鄒佳宏老師啟發，於2018年決意往指揮之路深造，應屆正取東吳大學音樂系研究所，主修管弦樂指揮，師從江靖波教授。就讀期間，曾受國家交響樂團音樂總監Jun Märkl、德國波鴻交響樂團音樂總監莊東杰、茱莉亞音樂學院指揮班辛明峰等國內外著名指揮家指導，並多次指揮東吳大學音樂系管弦樂團公開演出。\n現於建國中學樂旗隊、松山高中管樂團擔任指揮。自111學年度以來，已帶領兩校榮獲數次全國學生音樂比賽管樂合奏特優。此外，亦常受邀於雙北各級學校管樂團與校友管樂團擔任指揮。",
            "「叫我尚頤就好！」"
          ],
          [
            "高煜",
            "總召",
            "https://i.imgur.com/Syoa5x5.jpeg",
            "出生於臺灣臺北，畢業於國立臺灣藝術大學音樂研究所，取得長號碩士演奏文憑，師事周子揚教授。國中時期加入臺北市誠正國中管樂團，長號啟蒙於陳春瑾老師；於高中就讀期間決定報考音樂系，師事方崇任老師；大學畢業於文化大學音樂學系主修長號，師事梁兆豐教授。\n\n獨奏方面，於2016年與華岡交響管樂團合作演出Alexandre Guilmant: Morceau Symphonique擔任長號獨奏；並於2018年參與華岡之星協奏曲大賽獲第二名。2019年於蘆洲功學社音樂廳舉辦個人獨奏會；2023年與誠正國中校友管樂團演出Bert Appermont: Color for Trombone擔任長號獨奏。\n\n樂團演出方面，於2024年與藝享愛樂演出《古典X流行之粹》擔任長號演出人員；2024年與汐止愛樂樂團演出《汐止好Show音樂會系列》擔任長號演出人員；2023年與夢響管弦樂團演出《電影情深系列二》擔任長號演出人員；2023年與汐止愛樂樂團演出《汐止好Show!!》擔任長號演出人員；2023年與臺北市立交響樂團附設合唱團演出《永恆無暇之愛》擔任長號演出人員；2023年與汐止愛樂樂團演出《70週年鄧麗君紀念音樂會》擔任長號演出人員；2022年與國立臺灣交響樂團演出《諾特的神奇機器》音樂會擔任長號演出人員；2022年與台北青年管樂團二團演出《Fantasy Warrior》音樂會擔任長號首席；2019年與台北愛樂管弦樂團演出企業專場《搖擺豆芽》音樂會擔任長號演出人員；2019年與台北愛樂管弦樂團演出《太魯閣峽谷音樂會》擔任長號演出人員；2019年與台北愛樂管弦樂團演出《FGO電玩音樂會》擔任長號演出人員；2017年與台北市立交響樂團TSO pops擔任長號協演人員；2016年與奇岩室內樂團多次擔任長號演出人員。",
            "根據歐盟統計指出，在過去的 25 年，有高煜在的城市，就會發生乾旱。"
          ],
          [
            "駱繹",
            "副召",
            "https://i.imgur.com/hWWfmZF.jpeg",
            "「有自己的校友團吹，是一件非常幸福的事！」-大安高工校友團團長 李啟源\n\n《12輯》這場音樂會籌辦的過程真的很不容易，在眾多校友都已經沒有在吹樂器的時代，大家都因各自的人生而走上不一樣的道路，但…一起做音樂的心，一直都藏在心中的某處，要先感謝高老師再次提出辦理校友團的邀請，以「將大家聚在一起吹樂器。」的理念，點燃大家內心中那已昏暗多年的管樂魂，再次讓大家回憶了人生中，參加誠正管樂的美好時光，並想起那年我們的誓言 - 「一日誠管，終身誠管。」",
            "根據英國研究，平均十把薩克斯風，就有一把是駱繹親手擦過的。"
          ]
        ]
      },
      {
        "range": "'樂器'!A1:AB1001",
        "majorDimension": "ROWS",
        "values": [
          ["id", "group", "樂器", "instrument"],
          ["順序", "群組", "中文", "英文"],
          ["1", "1", "長笛", "Flute"],
          ["2", "2", "豎笛", "Clarinet"],
          ["3", "2", "低音豎笛", "Bass Clarinet"],
          ["4", "3", "高音薩克斯風", "Soprano Saxophone"],
          ["5", "3", "中音薩克斯風", "Alto Saxophone"],
          ["6", "3", "次中音薩克斯風", "Tenor Saxophone"],
          ["7", "3", "上低音薩克斯風", "Baritone Saxophone"],
          ["8", "4", "法國號", "French horn"],
          ["9", "5", "小號", "Trumpet"],
          ["10", "6", "長號", "Trombone"],
          ["11", "7", "上低音號", "Euphonium"],
          ["12", "8", "低音號", "Tuba"],
          ["13", "9", "打擊", "Percussion"],
          ["14", "9", "鋼琴", "Piano"]
        ]
      },
      {
        "range": "'其他'!A1:V1001",
        "majorDimension": "ROWS",
        "values": [
          ["項目", "內容"],
          ["這一排不可以更改"],
          [
            "樂團介紹",
            "誠正國中校友管樂團至今已成立十餘年。於2011年，創團人陳權號召眾多曾在誠正管樂中奏響過青春樂章的校友以及在校生們，共同在每年夏季參與演出。\n於是，每年的七、八月，誠正國中團練室裡，多了一群長得不像國中生的高中生、大學生以及社會人士，用他們僅有的時間揮灑汗水、淚水以及口水，為的就是譜出這場夏日盛宴。\n十年流轉，團員屆數甚差二十屆次，但透過音樂的力量，讓年紀的距離在彼此的心中淡化。他們透過自由奔放的音符，在樂聲中編織出校友與學弟妹之間的共鳴，消除了跨世代交流的阻礙，讓每個樂曲添加了動人的色彩。"
          ]
        ]
      }
    ]
  },
  "body": "{\n  \"spreadsheetId\": \"1gVZnMr8DYtQROQMmyHUTlbJAyrOjRhzV0W1kAxfQ0wk\",\n  \"valueRanges\": [\n    {\n      \"range\": \"'演出人員'!A1:Z997\",\n      \"majorDimension\": \"ROWS\",\n      \"values\": [\n        [\n          \"上台\",\n          \"名稱\",\n          \"樂器\",\n          \"屆數\"\n        ],\n        [\n          \"\",\n          \"中文姓名\",\n          \"\",\n          \"0,協演人員,-1,未知\"\n        ],\n        [\n          \"TRUE\",\n          \"陳逸慧\",\n          \"Flute\",\n          \"28\"\n        ],\n        [\n          \"TRUE\",\n          \"簡汎瑜\",\n          \"Flute\",\n          \"43\"\n        ],\n        [\n          \"TRUE\",\n          \"林唯媛\",\n          \"Flute\",\n          \"45\"\n        ],\n        [\n          \"TRUE\",\n          \"江品昀\",\n          \"Flute\",\n          \"47\"\n        ],\n        [\n          \"TRUE\",\n          \"陳玟育\",\n          \"Clarinet\",\n          \"36\"\n        ],\n        [\n          \"TRUE\",\n          \"翁育玟\",\n          \"Clarinet\",\n          \"37\"\n        ],\n        [\n          \"TRUE\",\n          \"吳宜蓁\",\n          \"Clarinet\",\n          \"0\"\n        ],\n        [\n          \"TRUE\",\n          \"呂晟智\",\n          \"Clarinet\",\n          \"0\"\n        ],\n        [\n          \"TRUE\",\n          \"陳敬宗\",\n          \"Clarinet\",\n          \"0\"\n        ],\n        [\n          \"TRUE\",\n          \"陳寶怡\",\n          \"Clarinet\",\n          \"0\"\n        ],\n        [\n          \"TRUE\",\n          \"紀宇珊\",\n          \"Alto Saxophone\",\n          \"32\"\n        ],\n        [\n          \"TRUE\",\n          \"張博翔\",\n          \"Alto Saxophone\",\n          \"43\"\n        ],\n        [\n          \"TRUE\",\n          \"戴丰恬\",\n          \"Alto Saxophone\",\n          \"46\"\n        ],\n        [\n          \"TRUE\",\n          \"謝嘉宜\",\n          \"Alto Saxophone\",\n          \"0\"\n        ],\n        [\n          \"TRUE\",\n          \"劉宥成\",\n          \"Tenor Saxophone\",\n          \"0\"\n        ],\n        [\n          \"TRUE\",\n          \"駱繹\",\n          \"Baritone Saxophone\",\n          \"35\"\n        ],\n        [\n          \"TRUE\",\n          \"蘇育銘\",\n          \"French horn\",\n          \"27\"\n        ],\n        [\n          \"TRUE\",\n          \"黃琬淑\",\n          \"French horn\",\n          \"31\"\n        ],\n        [\n          \"TRUE\",\n          \"莊畇琦\",\n          \"French horn\",\n          \"48\"\n        ],\n        [\n          \"TRUE\",\n          \"蘇雨桐\",\n          \"French horn\",\n          \"0\"\n        ],\n        [\n          \"TRUE\",\n          \"白芷綾\",\n          \"Trumpet\",\n          \"0\"\n        ],\n        [\n          \"TRUE\",\n          \"李浩維\",\n          \"Trumpet\",\n          \"0\"\n        ],\n        [\n          \"TRUE\",\n          \"陳柏睿\",\n          \"Trumpet\",\n          \"0\"\n        ],\n        [\n          \"TRUE\",\n          \"高煜\",\n          \"Trombone\",\n          \"34\"\n        ],\n        [\n          \"TRUE\",\n          \"鄭兆廷\",\n          \"Trombone\",\n          \"33\"\n        ],\n        [\n          \"TRUE\",\n          \"劉信成\",\n          \"Trombone\",\n          \"44\"\n        ],\n        [\n          \"TRUE\",\n          \"林思亮\",\n          \"Trombone\",\n          \"48\"\n        ],\n        [\n          \"TRUE\",\n          \"張明睿\",\n          \"Euphonium\",\n          \"26\"\n        ],\n        [\n          \"TRUE\",\n          \"陳克齊\",\n          \"Euphonium\",\n          \"38\"\n        ],\n        [\n          \"TRUE\",\n          \"陳函\",\n          \"Euphonium\",\n          \"0\"\n        ],\n        [\n          \"TRUE\",\n          \"王妤萱\",\n          \"Tuba\",\n          \"40\"\n        ],\n        [\n          \"TRUE\",\n          \"黃憫\",\n          \"Tuba\",\n          \"47\"\n        ],\n        [\n          \"TRUE\",\n          \"李承霖\",\n          \"Percussion\",\n          \"37\"\n        ],\n        [\n          \"TRUE\",\n          \"徐豊祺\",\n          \"Percussion\",\n          \"39\"\n        ],\n        [\n          \"TRUE\",\n          \"陳可馨\",\n          \"Percussion\",\n          \"46\"\n        ],\n        [\n          \"TRUE\",\n          \"鄭柏鳳\",\n          \"Percussion\",\n          \"46\"\n        ],\n        [\n          \"TRUE\",\n          \"王晉維\",\n          \"Percussion\",\n          \"46\"\n        ],\n        [\n          \"TRUE\",\n          \"吳承勳\",\n          \"Percussion\",\n          \"0\"\n        ],\n        [\n          \"TRUE\",\n          \"陳逸安\",\n          \"Piano\",\n          \"0\"\n        ]\n      ]\n    },\n    {\n      \"range\": \"'流程'!A1:AA1001\",\n      \"majorDimension\": \"ROWS\",\n      \"values\": [\n        [\n          \"曲序\",\n          \"公開活動\",\n          \"曲目/活動\",\n          \"小標題\",\n          \"時間\",\n          \"說明\"\n        ],\n        [\n          \"startFrom,1\",\n          \"encore 就不用勾\",\n          \"\",\n          \"作曲人,補充說明\",\n          \"分鐘 (曲目可略)\"\n        ],\n        [\n          \"1\",\n          \"TRUE\",\n          \"The Great Locomotive Chase\",\n          \"Robert W. Smith\",\n          \"\",\n          \"描繪了一場發生在美國內戰期間的著名火車追逐事件，該事件是一次大膽的軍事行動，發生在1862年4月12日，由聯邦軍隊試圖奪取並摧毀南方邦聯的鐵路和補給線。\\n一開始便展現出強烈的節奏感和緊張氣氛，模擬出火車的轟鳴聲和急速行駛的動態。隨著樂曲的發展，旋律變得越發激烈和充滿戲劇性，完美捕捉了追逐的緊迫感和緊張情勢。這首樂曲不僅展現了作曲家對歷史事件的深刻理解，也通過音樂的生動，再現了那段激動人心的歷史片段。\"\n        ],\n        [\n          \"2\",\n          \"TRUE\",\n          \"春よ、来い\",\n          \"鄉間幹男\",\n          \"\",\n          \"以溫柔而充滿情感的旋律著稱，表達了對春天到來的熱切期盼和對未來美好生活的憧憬。保留了原曲的細膩和溫暖，同時通過樂器間的配合與變化，賦予了它更多的層次感與表現力。當樂聲響起時，彷彿春天的氣息隨之撲面而來，為聽眾帶來無限的希望和美好的期待。\"\n        ],\n        [\n          \"3\",\n          \"TRUE\",\n          \"The Lord of the Dance\",\n          \"Richard Saucedo\",\n          \"\",\n          \"充滿活力與動感的作品，最初作為著名舞蹈劇《大河之舞》（Lord of the Dance）的主題曲而聞名。這首曲子以其強烈的節奏感和富有感染力的旋律，將愛爾蘭傳統音樂與現代編曲完美結合，是一首讓人不禁隨之起舞的動人作品。\"\n        ],\n        [\n          \"4\",\n          \"TRUE\",\n          \"Curtain Up!\",\n          \"Alfred Reed\",\n          \"\",\n          \"靈感來自於戲劇和音樂劇開場時的那份激動與期待感。正如其名，樂曲彷彿拉開了一場精彩表演的序幕，帶領聽眾進入一個充滿戲劇性和活力的音樂世界。\\n序曲結構豐富，開頭以宏大且充滿戲劇性的旋律引導聽眾，隨後進入輕快、活潑的中段，展示出各種不同音樂風格的交織與變化。Reed運用了豐富的管樂編排技巧，讓每一個樂器組都能發揮其獨特的音色，從而營造出多層次的音樂效果。\"\n        ],\n        [\n          \"5\",\n          \"TRUE\",\n          \"The Lion King\",\n          \"John Higgins\",\n          \"\",\n          \"改編自迪士尼經典動畫《獅子王》的音樂，原作音樂由漢斯·季默（Hans Zimmer）和埃爾頓·約翰（Elton John）創作，旋律耳熟能詳，充滿非洲特色的節奏和旋律，將獅子王辛巴的冒險故事與生命循環的主題完美結合。這些曲目包括《Circle of Life》、《Hakuna Matata》、《Can You Feel the Love Tonight》等，皆已成為跨世代的經典。音樂在柔和與強烈之間不斷轉換，展現了從生命的開端到榮耀歸來的壯麗旅程。\"\n        ],\n        [\n          \"\",\n          \"TRUE\",\n          \"中場休息\",\n          \"休息 15 分鐘\",\n          \"15\"\n        ],\n        [\n          \"6\",\n          \"TRUE\",\n          \"Symphonic Episode 1\",\n          \"Satoshi Yagisawa\",\n          \"\",\n          \"樂曲的主題充滿戲劇性，從一開始便展現出莊嚴而充滿力量的氛圍。隨著音樂的推進，旋律逐漸變得緊湊和複雜，展現出作曲家精湛的編曲技巧。樂曲中穿插著細膩的抒情段落與強烈的音樂對比，從而構建了一個既有深度又富有動感的音樂旅程。\"\n        ],\n        [\n          \"7\",\n          \"TRUE\",\n          \"Mulan\",\n          \"Johnie Vinson\",\n          \"\",\n          \"電影《花木蘭》以中國古代的木蘭傳說為背景，描述了一位勇敢的少女木蘭女扮男裝替父從軍，最終成為英雄的故事，曲子完美融合了中國傳統音樂的元素與西方交響樂的氣勢。樂曲中既有柔美細膩的旋律，也有充滿張力的片段，生動地展現了木蘭從少女到戰士的成長歷程。\"\n        ],\n        [\n          \"8\",\n          \"TRUE\",\n          \"J-POP Stage Vol-3\",\n          \"山里佐和子\",\n          \"\",\n          \"著名日本動畫《海賊王》（One Piece）的經典樂曲組曲，匯集了動畫中多首耳熟能詳的曲目，通過管樂的形式重現了《海賊王》中那些充滿冒險、友情與夢想的感人時刻。音樂隨著劇情的發展而變化，時而激昂、時而抒情，完美捕捉了動畫中那股無畏的冒險精神和深厚的夥伴情誼。\"\n        ],\n        [\n          \"9\",\n          \"TRUE\",\n          \" Idol\",\n          \"\",\n          \"\",\n          \"日本動畫《我推的孩子》主題曲，以輕快的節奏、明亮的旋律和充滿青春氣息的編曲，生動地捕捉了流行音樂的精髓。旋律簡單卻極具吸引力，能夠讓人不由自主地跟隨節奏搖擺。\"\n        ],\n        [\n          \"\",\n          \"TRUE\",\n          \"誠正校歌\",\n          \"\",\n          \"\",\n          \"綠水長流　層山長青　斯地創校　毓秀鐘英\\n復興文化　誠正是崇　我校其名　宏開世風\\n健全國民　五育並重　仁為己任　善與人同\\n莊敬自強　日新月盛　學以報國　治至以隆\"\n        ]\n      ]\n    },\n    {\n      \"range\": \"'介紹'!A1:Y1001\",\n      \"majorDimension\": \"ROWS\",\n      \"values\": [\n        [\n          \"姓名\",\n          \"職稱\",\n          \"照片\",\n          \"介紹\",\n          \"quote\"\n        ],\n        [\n          \"\",\n          \"\",\n          \"請放連結\",\n          \"長文介紹，用\\\",\\\"做分段\"\n        ],\n        [\n          \"林尚頤\",\n          \"指揮\",\n          \"https://i.imgur.com/YS3IFiS.jpeg\",\n          \"臺北人，求學生涯曾就讀光仁小學、弘道國中、建國中學、臺北大學，並於大學時期初次接受正規指揮課程，師從王戰老師。除此之外，參加北大管樂團期間亦深受指揮鄒佳宏老師啟發，於2018年決意往指揮之路深造，應屆正取東吳大學音樂系研究所，主修管弦樂指揮，師從江靖波教授。就讀期間，曾受國家交響樂團音樂總監Jun Märkl、德國波鴻交響樂團音樂總監莊東杰、茱莉亞音樂學院指揮班辛明峰等國內外著名指揮家指導，並多次指揮東吳大學音樂系管弦樂團公開演出。\\n現於建國中學樂旗隊、松山高中管樂團擔任指揮。自111學年度以來，已帶領兩校榮獲數次全國學生音樂比賽管樂合奏特優。此外，亦常受邀於雙北各級學校管樂團與校友管樂團擔任指揮。\",\n          \"「叫我尚頤就好！」\"\n        ],\n        [\n          \"高煜\",\n          \"總召\",\n          \"https://i.imgur.com/Syoa5x5.jpeg\",\n          \"出生於臺灣臺北，畢業於國立臺灣藝術大學音樂研究所，取得長號碩士演奏文憑，師事周子揚教授。國中時期加入臺北市誠正國中管樂團，長號啟蒙於陳春瑾老師；於高中就讀期間決定報考音樂系，師事方崇任老師；大學畢業於文化大學音樂學系主修長號，師事梁兆豐教授。\\n\\n獨奏方面，於2016年與華岡交響管樂團合作演出Alexandre Guilmant: Morceau Symphonique擔任長號獨奏；並於2018年參與華岡之星協奏曲大賽獲第二名。2019年於蘆洲功學社音樂廳舉辦個人獨奏會；2023年與誠正國中校友管樂團演出Bert Appermont: Color for Trombone擔任長號獨奏。\\n\\n樂團演出方面，於2024年與藝享愛樂演出《古典X流行之粹》擔任長號演出人員；2024年與汐止愛樂樂團演出《汐止好Show音樂會系列》擔任長號演出人員；2023年與夢響管弦樂團演出《電影情深系列二》擔任長號演出人員；2023年與汐止愛樂樂團演出《汐止好Show!!》擔任長號演出人員；2023年與臺北市立交響樂團附設合唱團演出《永恆無暇之愛》擔任長號演出人員；2023年與汐止愛樂樂團演出《70週年鄧麗君紀念音樂會》擔任長號演出人員；2022年與國立臺灣交響樂團演出《諾特的神奇機器》音樂會擔任長號演出人員；2022年與台北青年管樂團二團演出《Fantasy Warrior》音樂會擔任長號首席；2019年與台北愛樂管弦樂團演出企業專場《搖擺豆芽》音樂會擔任長號演出人員；2019年與台北愛樂管弦樂團演出《太魯閣峽谷音樂會》擔任長號演出人員；2019年與台北愛樂管弦樂團演出《FGO電玩音樂會》擔任長號演出人員；2017年與台北市立交響樂團TSO pops擔任長號協演人員；2016年與奇岩室內樂團多次擔任長號演出人員。\",\n          \"根據歐盟統計指出，在過去的 25 年，有高煜在的城市，就會發生乾旱。\"\n        ],\n        [\n          \"駱繹\",\n          \"副召\",\n          \"https://i.imgur.com/hWWfmZF.jpeg\",\n          \"「有自己的校友團吹，是一件非常幸福的事！」-大安高工校友團團長 李啟源\\n\\n《12輯》這場音樂會籌辦的過程真的很不容易，在眾多校友都已經沒有在吹樂器的時代，大家都因各自的人生而走上不一樣的道路，但…一起做音樂的心，一直都藏在心中的某處，要先感謝高老師再次提出辦理校友團的邀請，以「將大家聚在一起吹樂器。」的理念，點燃大家內心中那已昏暗多年的管樂魂，再次讓大家回憶了人生中，參加誠正管樂的美好時光，並想起那年我們的誓言 - 「一日誠管，終身誠管。」\",\n          \"根據英國研究，平均十把薩克斯風，就有一把是駱繹親手擦過的。\"\n        ]\n      ]\n    },\n    {\n      \"range\": \"'樂器'!A1:AB1001\",\n      \"majorDimension\": \"ROWS\",\n      \"values\": [\n        [\n          \"id\",\n          \"group\",\n          \"樂器\",\n          \"instrument\"\n        ],\n        [\n          \"順序\",\n          \"群組\",\n          \"中文\",\n          \"英文\"\n        ],\n        [\n          \"1\",\n          \"1\",\n          \"長笛\",\n          \"Flute\"\n        ],\n        [\n          \"2\",\n          \"2\",\n          \"豎笛\",\n          \"Clarinet\"\n        ],\n        [\n          \"3\",\n          \"2\",\n          \"低音豎笛\",\n          \"Bass Clarinet\"\n        ],\n        [\n          \"4\",\n          \"3\",\n          \"高音薩克斯風\",\n          \"Soprano Saxophone\"\n        ],\n        [\n          \"5\",\n          \"3\",\n          \"中音薩克斯風\",\n          \"Alto Saxophone\"\n        ],\n        [\n          \"6\",\n          \"3\",\n          \"次中音薩克斯風\",\n          \"Tenor Saxophone\"\n        ],\n        [\n          \"7\",\n          \"3\",\n          \"上低音薩克斯風\",\n          \"Baritone Saxophone\"\n        ],\n        [\n          \"8\",\n          \"4\",\n          \"法國號\",\n          \"French horn\"\n        ],\n        [\n          \"9\",\n          \"5\",\n          \"小號\",\n          \"Trumpet\"\n        ],\n        [\n          \"10\",\n          \"6\",\n          \"長號\",\n          \"Trombone\"\n        ],\n        [\n          \"11\",\n          \"7\",\n          \"上低音號\",\n          \"Euphonium\"\n        ],\n        [\n          \"12\",\n          \"8\",\n          \"低音號\",\n          \"Tuba\"\n        ],\n        [\n          \"13\",\n          \"9\",\n          \"打擊\",\n          \"Percussion\"\n        ],\n        [\n          \"14\",\n          \"9\",\n          \"鋼琴\",\n          \"Piano\"\n        ]\n      ]\n    },\n    {\n      \"range\": \"'其他'!A1:V1001\",\n      \"majorDimension\": \"ROWS\",\n      \"values\": [\n        [\n          \"項目\",\n          \"內容\"\n        ],\n        [\n          \"這一排不可以更改\"\n        ],\n        [\n          \"樂團介紹\",\n          \"誠正國中校友管樂團至今已成立十餘年。於2011年，創團人陳權號召眾多曾在誠正管樂中奏響過青春樂章的校友以及在校生們，共同在每年夏季參與演出。\\n於是，每年的七、八月，誠正國中團練室裡，多了一群長得不像國中生的高中生、大學生以及社會人士，用他們僅有的時間揮灑汗水、淚水以及口水，為的就是譜出這場夏日盛宴。\\n十年流轉，團員屆數甚差二十屆次，但透過音樂的力量，讓年紀的距離在彼此的心中淡化。他們透過自由奔放的音符，在樂聲中編織出校友與學弟妹之間的共鳴，消除了跨世代交流的阻礙，讓每個樂曲添加了動人的色彩。\"\n        ]\n      ]\n    }\n  ]\n}\n",
  "headers": {
    "cache-control": "private",
    "content-encoding": "gzip",
    "content-length": "6159",
    "content-type": "application/json; charset=UTF-8",
    "date": "Fri, 23 Aug 2024 17:02:27 GMT",
    "server": "ESF",
    "vary": "Origin, X-Origin, Referer"
  },
  "status": 200,
  "statusText": null
}
